common/__init__.py
common/core.py
main/__init__.py
main/main.py
phat_main/__init__.py
phat_main/main.py
phat_tool-0.54.data/scripts/phat
phat_tool-0.54.data/scripts/settings.py
plugins/CompareURLs/__init__.py
plugins/CompareURLs/plugin.py
plugins/CompareURLs/test.py
plugins/FollowLinks/__init__.py
plugins/FollowLinks/plugin.py
plugins/FollowLinks/test.py
plugins/HTMLoutput/__init__.py
plugins/HTMLoutput/plugin.py
plugins/JUnit/__init__.py
plugins/JUnit/plugin.py
plugins/JsonApi/__init__.py
plugins/JsonApi/plugin.py
plugins/JsonApi/test.py
plugins/Regex/__init__.py
plugins/Regex/plugin.py
plugins/Regex/test.py
plugins/ResponseCookies/__init__.py
plugins/ResponseCookies/plugin.py
plugins/ResponseCookies/test.py
plugins/ResponseHeaders/__init__.py
plugins/ResponseHeaders/plugin.py
plugins/ResponseHeaders/test.py
plugins/RunBrowser/__init__.py
plugins/RunBrowser/plugin.py
plugins/Selenium/__init__.py
plugins/Selenium/plugin.py
plugins/StatusCode/__init__.py
plugins/StatusCode/plugin.py
plugins/StatusCode/test.py
plugins/TimeMe/__init__.py
plugins/TimeMe/plugin.py
phat_tool-0.54.dist-info/LICENSE
phat_tool-0.54.dist-info/METADATA
phat_tool-0.54.dist-info/WHEEL
phat_tool-0.54.dist-info/top_level.txt
phat_tool-0.54.dist-info/RECORD
