Metadata-Version: 2.1
Name: phat-tool
Version: 0.54
Summary: Pluggable HTTP Auto Testing
Home-page: https://github.com/danielfranca/phat
Author: Daniel Franca
Author-email: UNKNOWN
License: MIT
Platform: UNKNOWN
Requires-Dist: python-Levenshtein (>=0.11.2)
Requires-Dist: beautifulsoup4 (>=4.4.1)
Requires-Dist: requests (>=2.5.0)
Requires-Dist: paramiko (>=1.15.2)
Requires-Dist: jsonpath-rw (>=1.4.0)
Requires-Dist: selenium (>=2.53.2)
Requires-Dist: responses (>=0.5.1)
